{
  "resourceType" : "CodeSystem",
  "id" : "7fbe33db-5687-46e7-b130-f6218251d011-20",
  "url" : "http://hl7.org/fhir/comparison/CodeSystem/7fbe33db-5687-46e7-b130-f6218251d011-20",
  "name" : "UnionPriorAuthorizationValueCodesAndPriorAuthorizationValueCodes",
  "title" : "Union of Prior Authorization Values And Prior Authorization Values",
  "status" : "active",
  "date" : "2024-01-03T13:33:53-05:00",
  "jurisdiction" : [{
    "coding" : [{
      "system" : "urn:iso:std:iso:3166",
      "code" : "US",
      "display" : "United States of America"
    }]
  }],
  "concept" : [{
    "code" : "submitted",
    "display" : "Submitted",
    "definition" : "Proposed amounts of units or services"
  },
  {
    "code" : "eligible",
    "display" : "Eligible",
    "definition" : "Eligible/agreed items or services"
  },
  {
    "code" : "utilized",
    "display" : "Utilized",
    "definition" : "Amount of items or services consumed to date"
  }]
}